__init__.py
crypter_config.py
crypter_db.py
crypter_main.py
crypter_token_generator.py
localvault-1.0.1.dist-info/LICENSE
localvault-1.0.1.dist-info/METADATA
localvault-1.0.1.dist-info/WHEEL
localvault-1.0.1.dist-info/entry_points.txt
localvault-1.0.1.dist-info/top_level.txt
localvault-1.0.1.dist-info/RECORD
