Metadata-Version: 2.1
Name: localvault
Version: 1.0.1
Summary: A command line utility to generate/store random passwords for the given username/key.
Author-email: Mukul Taneja <mukultaneja91@gmail.com>
License: BSD 3-Clause License
Project-URL: Homepage, https://github.com/mukultaneja/crypter
Keywords: encryption,password-generator,CLI utility
Classifier: License :: OSI Approved :: BSD License
Classifier: Programming Language :: Python
Classifier: Programming Language :: Python :: 3
Requires-Python: >=3.6
License-File: LICENSE
Requires-Dist: click
Requires-Dist: sqlalchemy
Requires-Dist: cryptography
Requires-Dist: prettytable
